Metadata-Version: 2.1
Name: imagebaker
Version: 0.52
Summary: A package for baking images.
Home-page: https://github.com/q-viper/Image-Baker
Author: Ramkrishna Acharya
Author-email: qramkrishna@gmail.com
License: MIT
Classifier: Programming Language :: Python :: 3
Classifier: License :: OSI Approved :: MIT License
Classifier: Operating System :: OS Independent
Requires-Python: >=3.10
License-File: LICENSE
Requires-Dist: numpy>=1.21
Requires-Dist: matplotlib>=3.4
Requires-Dist: opencv-python>=4.5
Requires-Dist: black>=23.1
Requires-Dist: pydantic>=2.11.1
Requires-Dist: flake8>=6.0
Requires-Dist: typer>=0.9
Requires-Dist: PySide6==6.8.3
Requires-Dist: loguru
Provides-Extra: docs
Requires-Dist: mkdocs>=1.4; extra == "docs"
Requires-Dist: mkdocs-material>=9.0; extra == "docs"
Requires-Dist: mkdocstrings[python]>=0.21; extra == "docs"
Requires-Dist: pymdown-extensions>=8.0; extra == "docs"
Requires-Dist: mkdocs-awesome-pages-plugin; extra == "docs"
